paul_mclendahand/__init__.py
paul_mclendahand/cmd_pmac.py
paul_mclendahand-3.2.1.dist-info/LICENSE
paul_mclendahand-3.2.1.dist-info/METADATA
paul_mclendahand-3.2.1.dist-info/WHEEL
paul_mclendahand-3.2.1.dist-info/entry_points.txt
paul_mclendahand-3.2.1.dist-info/top_level.txt
paul_mclendahand-3.2.1.dist-info/RECORD
