Metadata-Version: 2.1
Name: paul-mclendahand
Version: 3.2.1
Summary: Tool for combining GitHub pull requests.
Author: Will Kahn-Greene
License: MPLv2
Project-URL: Homepage, https://github.com/willkg/paul-mclendahanad
Project-URL: Source, https://github.com/willkg/paul-mclendahanad
Project-URL: Issues, https://github.com/willkg/paul-mclendahanad/issues
Keywords: github,pr
Classifier: Development Status :: 5 - Production/Stable
Classifier: Intended Audience :: Developers
Classifier: License :: OSI Approved :: Mozilla Public License 2.0 (MPL 2.0)
Classifier: Natural Language :: English
Classifier: Programming Language :: Python :: 3 :: Only
Classifier: Programming Language :: Python :: 3.9
Classifier: Programming Language :: Python :: 3.10
Classifier: Programming Language :: Python :: 3.11
Classifier: Programming Language :: Python :: 3.12
Classifier: Programming Language :: Python :: 3.13
Requires-Python: >=3.9
License-File: LICENSE
Requires-Dist: click
Requires-Dist: importlib_metadata
Requires-Dist: rich
Requires-Dist: tomli>=1.1.0; python_version < "3.11"
Provides-Extra: dev
Requires-Dist: build; extra == "dev"
Requires-Dist: cogapp; extra == "dev"
Requires-Dist: pytest; extra == "dev"
Requires-Dist: ruff; extra == "dev"
Requires-Dist: setuptools; extra == "dev"
Requires-Dist: twine; extra == "dev"
Requires-Dist: tox; extra == "dev"
Requires-Dist: tox-gh-actions; extra == "dev"
Requires-Dist: tox-uv; extra == "dev"
